setup.cfg
setup.py
supervisor_checks/__init__.py
supervisor_checks/check_runner.py
supervisor_checks/compat.py
supervisor_checks/errors.py
supervisor_checks/utils.py
supervisor_checks.egg-info/PKG-INFO
supervisor_checks.egg-info/SOURCES.txt
supervisor_checks.egg-info/dependency_links.txt
supervisor_checks.egg-info/entry_points.txt
supervisor_checks.egg-info/requires.txt
supervisor_checks.egg-info/top_level.txt
supervisor_checks/bin/__init__.py
supervisor_checks/bin/complex_check.py
supervisor_checks/bin/cpu_check.py
supervisor_checks/bin/http_check.py
supervisor_checks/bin/memory_check.py
supervisor_checks/bin/tcp_check.py
supervisor_checks/bin/xmlrpc_check.py
supervisor_checks/check_modules/__init__.py
supervisor_checks/check_modules/base.py
supervisor_checks/check_modules/cpu.py
supervisor_checks/check_modules/http.py
supervisor_checks/check_modules/memory.py
supervisor_checks/check_modules/tcp.py
supervisor_checks/check_modules/xmlrpc.py