Metadata-Version: 1.1
Name: supervisor-checks
Version: 0.8.1
Summary: Framework to build health checks for Supervisor-based services.
Home-page: https://github.com/vovanec/supervisor_checks
Author: Vovan Kuznetsov
Author-email: vovanec@gmail.com
License: MIT
Download-URL: https://github.com/vovanec/supervisor_checks/tarball/0.8.1
Keywords: supervisor,event,listener,eventlistener,http,memory,xmlrpc,health,check,monitor,cpu
Platform: UNKNOWN
Classifier: License :: OSI Approved :: MIT License
Classifier: Development Status :: 4 - Beta
Classifier: Intended Audience :: Developers
Classifier: Operating System :: POSIX
Classifier: Topic :: System :: Boot
Classifier: Topic :: System :: Monitoring
Classifier: Topic :: System :: Systems Administration
Classifier: Programming Language :: Python
Classifier: Programming Language :: Python :: 2
Classifier: Programming Language :: Python :: 2.6
Classifier: Programming Language :: Python :: 2.7
Classifier: Programming Language :: Python :: 3
Classifier: Programming Language :: Python :: 3.2
Classifier: Programming Language :: Python :: 3.3
Classifier: Programming Language :: Python :: 3.4
